MANIFEST.in
RELEASE-VERSION
setup.py
version.py
src/sortedcollection/__init__.py
src/sortedcollection/test_sorted_collection.py
src/sortedcollection.egg-info/PKG-INFO
src/sortedcollection.egg-info/SOURCES.txt
src/sortedcollection.egg-info/dependency_links.txt
src/sortedcollection.egg-info/requires.txt
src/sortedcollection.egg-info/top_level.txt