Metadata-Version: 1.1
Name: sortedcollection
Version: 0.1.7
Summary: SortedCollection class that abstracts bisect extended from http://code.activestate.com/recipes/577197-sortedcollection/.
Home-page: UNKNOWN
Author: Diffeo, Inc.
Author-email: support@diffeo.com
License: UNKNOWN
Platform: UNKNOWN
Classifier: Development Status :: 3 - Alpha
Classifier: Topic :: Utilities
Classifier: License :: OSI Approved :: MIT License
